Metadata-Version: 2.1
Name: pythonwithinfinity
Version: 0.0.3
Summary: **PyInfinity License**
Home-page: https://www.allwithinfinity.com
Author: Matvei Kostenko
Author-email: kmatvij71@gmail.com
License: **PyInfinity License**
Project-URL: Documentation, https://www.allwithinfinity.com/docs
Keywords: python framework utilities PyInfinity
Classifier: Development Status :: 2 - Pre-Alpha
Classifier: Intended Audience :: Developers
Classifier: License :: Other/Proprietary License
Classifier: Programming Language :: Python :: 3.12
Classifier: Operating System :: POSIX
Classifier: Operating System :: Microsoft :: Windows
Classifier: Topic :: Software Development :: Libraries :: Python Modules
Classifier: Topic :: Software Development :: Libraries
Classifier: Topic :: Utilities
Requires-Python: >=3.12
